odoo/addons/base_external_dbsource_sap_hana/README.rst
odoo/addons/base_external_dbsource_sap_hana/__init__.py
odoo/addons/base_external_dbsource_sap_hana/__manifest__.py
odoo/addons/base_external_dbsource_sap_hana/demo/base_external_dbsource.xml
odoo/addons/base_external_dbsource_sap_hana/i18n/base_external_dbsource_sap_hana.pot
odoo/addons/base_external_dbsource_sap_hana/i18n/es.po
odoo/addons/base_external_dbsource_sap_hana/models/__init__.py
odoo/addons/base_external_dbsource_sap_hana/models/base_external_dbsource.py
odoo/addons/base_external_dbsource_sap_hana/readme/CONFIGURE.rst
odoo/addons/base_external_dbsource_sap_hana/readme/CONTRIBUTORS.rst
odoo/addons/base_external_dbsource_sap_hana/readme/DESCRIPTION.rst
odoo/addons/base_external_dbsource_sap_hana/readme/INSTALL.rst
odoo/addons/base_external_dbsource_sap_hana/readme/USAGE.rst
odoo/addons/base_external_dbsource_sap_hana/static/description/icon.png
odoo/addons/base_external_dbsource_sap_hana/static/description/index.html
odoo/addons/base_external_dbsource_sap_hana/tests/__init__.py
odoo/addons/base_external_dbsource_sap_hana/tests/test_base_external_dbsource_sap_hana.py
odoo_addon_base_external_dbsource_sap_hana-15.0.1.0.0.4.dist-info/METADATA
odoo_addon_base_external_dbsource_sap_hana-15.0.1.0.0.4.dist-info/WHEEL
odoo_addon_base_external_dbsource_sap_hana-15.0.1.0.0.4.dist-info/top_level.txt
odoo_addon_base_external_dbsource_sap_hana-15.0.1.0.0.4.dist-info/RECORD
