Metadata-Version: 2.1
Name: odoo-addon-base-external-dbsource-sap-hana
Version: 15.0.1.0.0.4
Summary: External Database Source - SAP - Hana
Home-page: https://github.com/OCA/server-backend
Author: Tecnativa, Odoo Community Association (OCA)
Author-email: support@odoo-community.org
License: LGPL-3
Platform: UNKNOWN
Classifier: Programming Language :: Python
Classifier: Framework :: Odoo
Classifier: Framework :: Odoo :: 15.0
Classifier: License :: OSI Approved :: GNU Lesser General Public License v3 (LGPLv3)
Requires-Python: >=3.8
Requires-Dist: hdbcli
Requires-Dist: odoo-addon-base-external-dbsource <15.1dev,>=15.0dev
Requires-Dist: odoo <15.1dev,>=15.0a
Requires-Dist: sqlalchemy
Requires-Dist: sqlalchemy-hana
